{"_type":"export","__export_format":4,"__export_date":"2023-06-15T19:37:50.476Z","__export_source":"insomnia.desktop.app:v2023.2.2","resources":[{"_id":"req_1313c7331e9145eb80bacc187e0181ae","parentId":"fld_39737a6fd62d445dba7fae65d4e96bfb","modified":1686855706274,"created":1686593600390,"url":"http://localhost:8080/venda/atualizar/1","name":"Atualizar","description":"","method":"PUT","body":{"mimeType":"application/json","text":"{\n\t\"id\": 1,\n\t\"cadastro\": \"2023-06-12T18:14:04.097+00:00\",\n\t\"identificacao\": \"1266666666665\",\n\t\"funcionario\": {\n\t\t\"id\": 2,\n\t\t\"nome\": \"Carlos Eduardo Falandes\",\n\t\t\"nomeSocial\": \"Edu\",\n\t\t\"perfis\": [\n\t\t\t\"FUNCIONARIO\"\n\t\t],\n\t\t\"telefones\": [\n\t\t\t{\n\t\t\t\t\"id\": 2,\n\t\t\t\t\"ddd\": \"012\",\n\t\t\t\t\"numero\": \"988372758\"\n\t\t\t}\n\t\t],\n\t\t\"endereco\": {\n\t\t\t\"id\": 3,\n\t\t\t\"estado\": \"São Paulo\",\n\t\t\t\"cidade\": \"São José dos Campos\",\n\t\t\t\"bairro\": \"Interlagos\",\n\t\t\t\"rua\": \"Rua. Antônio Boarini\",\n\t\t\t\"numero\": \"3000\",\n\t\t\t\"codigoPostal\": \"12229-130\",\n\t\t\t\"informacoesAdicionais\": null\n\t\t},\n\t\t\"documentos\": [\n\t\t\t{\n\t\t\t\t\"id\": 2,\n\t\t\t\t\"tipo\": \"CPF\",\n\t\t\t\t\"dataEmissao\": \"2023-06-12T18:14:04.097+00:00\",\n\t\t\t\t\"numero\": \"49985842863\"\n\t\t\t}\n\t\t],\n\t\t\"emails\": [\n\t\t\t{\n\t\t\t\t\"id\": 2,\n\t\t\t\t\"endereco\": \"edu@gmail.com\"\n\t\t\t}\n\t\t],\n\t\t\"credenciais\": [\n\t\t\t{\n\t\t\t\t\"id\": 2,\n\t\t\t\t\"criacao\": \"2023-06-12T18:14:04.097+00:00\",\n\t\t\t\t\"ultimoAcesso\": \"2023-06-12T18:14:04.097+00:00\",\n\t\t\t\t\"inativo\": false,\n\t\t\t\t\"nomeUsuario\": \"carlosfalandes\",\n\t\t\t\t\"senha\": \"fatec\"\n\t\t\t}\n\t\t],\n\t\t\"mercadorias\": [],\n\t\t\"vendas\": [],\n\t\t\"veiculos\": []\n\t},\n\t\"mercadorias\": [\n\t\t{\n\t\t\t\"id\": 1,\n\t\t\t\"validade\": \"2023-06-12T18:14:04.097+00:00\",\n\t\t\t\"fabricao\": \"2023-06-12T18:14:04.097+00:00\",\n\t\t\t\"cadastro\": \"2023-06-12T18:14:04.097+00:00\",\n\t\t\t\"nome\": \"Roda de liga leve modelo Volkswagen Golf\",\n\t\t\t\"quantidade\": 50,\n\t\t\t\"valor\": 350.0,\n\t\t\t\"descricao\": \"Roda de liga leve original de fábrica da Volkswagen para modelos do tipo hatchback\"\n\t\t}\n\t],\n\t\"servicos\": [\n\t\t{\n\t\t\t\"id\": 1,\n\t\t\t\"nome\": \"Troca de rodas esportivas\",\n\t\t\t\"valor\": 150.0,\n\t\t\t\"descricao\": \"Substituição das rodas do carro por modelos esportivos\"\n\t\t}\n\t]}"},"parameters":[],"headers":[{"name":"Content-Type","value":"application/json"}],"authentication":{},"metaSortKey":-1686592591082,"isPrivate":false,"settingStoreCookies":true,"settingSendCookies":true,"settingDisableRenderRequestBody":false,"settingEncodeUrl":true,"settingRebuildPath":true,"settingFollowRedirects":"global","_type":"request"},{"_id":"fld_39737a6fd62d445dba7fae65d4e96bfb","parentId":"wrk_0b32a91f72644d56a1e198cfc3dcaf96","modified":1686593600368,"created":1686593600368,"name":"Venda","description":"","environment":{},"environmentPropertyOrder":null,"metaSortKey":-1686591741442.1094,"_type":"request_group"},{"_id":"wrk_0b32a91f72644d56a1e198cfc3dcaf96","parentId":null,"modified":1686857813598,"created":1686857813598,"name":"Untitled","description":"","scope":"design","_type":"workspace"},{"_id":"req_1a5db3cff5f644feb800ad7164a0de82","parentId":"fld_39737a6fd62d445dba7fae65d4e96bfb","modified":1686857277440,"created":1686593600386,"url":"http://localhost:8080/venda/cadastrar/1","name":"Cadastro","description":"","method":"POST","body":{"mimeType":"application/json","text":"{\n\t\"cadastro\": \"2023-06-12T18:14:04.097+00:00\",\n\t\"identificacao\": \"1234698745\",\n\t\"funcionario\": {\n\t\t\"id\": 2,\n\t\t\"nome\": \"Carlos Eduardo Falandes\",\n\t\t\"nomeSocial\": \"Edu\",\n\t\t\"perfis\": [\n\t\t\t\"FUNCIONARIO\"\n\t\t]\n\t}}"},"parameters":[],"headers":[{"name":"Content-Type","value":"application/json"}],"authentication":{},"metaSortKey":-1686592515480,"isPrivate":false,"settingStoreCookies":true,"settingSendCookies":true,"settingDisableRenderRequestBody":false,"settingEncodeUrl":true,"settingRebuildPath":true,"settingFollowRedirects":"global","_type":"request"},{"_id":"req_961becb36c9748bb9cdcf83408786289","parentId":"fld_39737a6fd62d445dba7fae65d4e96bfb","modified":1686857282317,"created":1686593600380,"url":"http://localhost:8080/venda/venda/1","name":"Venda especifica","description":"","method":"GET","body":{},"parameters":[],"headers":[],"authentication":{},"metaSortKey":-1686592471109,"isPrivate":false,"settingStoreCookies":true,"settingSendCookies":true,"settingDisableRenderRequestBody":false,"settingEncodeUrl":true,"settingRebuildPath":true,"settingFollowRedirects":"global","_type":"request"},{"_id":"req_a6ed01fbe95b43f68999f4e5aa8f2e31","parentId":"fld_39737a6fd62d445dba7fae65d4e96bfb","modified":1686857288605,"created":1686593600372,"url":"http://localhost:8080/venda/vendas","name":"Visualizar","description":"","method":"GET","body":{},"parameters":[],"headers":[],"authentication":{},"metaSortKey":-1686592405521,"isPrivate":false,"settingStoreCookies":true,"settingSendCookies":true,"settingDisableRenderRequestBody":false,"settingEncodeUrl":true,"settingRebuildPath":true,"settingFollowRedirects":"global","_type":"request"},{"_id":"req_1785066243f14949b18e16e92659e669","parentId":"fld_6e1fe355c9a04ce98030968a350be86c","modified":1686593550404,"created":1686593371833,"url":"http://localhost:8080/veiculo/excluir/1","name":"Deletar","description":"","method":"DELETE","body":{"mimeType":"application/json","text":"{\n\t\"id\": 1\n}"},"parameters":[],"headers":[{"name":"Content-Type","value":"application/json"}],"authentication":{},"metaSortKey":-1686592671298,"isPrivate":false,"settingStoreCookies":true,"settingSendCookies":true,"settingDisableRenderRequestBody":false,"settingEncodeUrl":true,"settingRebuildPath":true,"settingFollowRedirects":"global","_type":"request"},{"_id":"fld_6e1fe355c9a04ce98030968a350be86c","parentId":"wrk_0b32a91f72644d56a1e198cfc3dcaf96","modified":1686593604457,"created":1686593371773,"name":"Veiculo ","description":"","environment":{},"environmentPropertyOrder":null,"metaSortKey":-1686591715962.3828,"_type":"request_group"},{"_id":"req_20fd4adc2e144c93b265996935d69bdb","parentId":"fld_6e1fe355c9a04ce98030968a350be86c","modified":1686855690287,"created":1686593371821,"url":"http://localhost:8080/veiculo/atualizar/1","name":"Atualizar","description":"","method":"PUT","body":{"mimeType":"application/json","text":"{\n\t\"id\": 1,\n\t\"tipo\": \"SUV\",\n\t\"modelo\": \"Goaaaaaaaaaal\",\n\t\"placa\": \"XYZ-1234\",\n\t\"vendas\": [\n\t\t{\n\t\t\t\"id\": 1,\n\t\t\t\"cadastro\": \"2023-06-12T18:09:57.238+00:00\",\n\t\t\t\"identificacao\": \"1234698745\",\n\t\t\t\"funcionario\": {\n\t\t\t\t\"id\": 1,\n\t\t\t\t\"nome\": \"Carlos Eduardo Falandes\",\n\t\t\t\t\"nomeSocial\": \"Edu\",\n\t\t\t\t\"perfis\": [\n\t\t\t\t\t\"FUNCIONARIO\"\n\t\t\t\t],\n\t\t\t\t\"telefones\": [\n\t\t\t\t\t{\n\t\t\t\t\t\t\"id\": 2,\n\t\t\t\t\t\t\"ddd\": \"012\",\n\t\t\t\t\t\t\"numero\": \"988372758\"\n\t\t\t\t\t}\n\t\t\t\t],\n\t\t\t\t\"endereco\": {\n\t\t\t\t\t\"id\": 2,\n\t\t\t\t\t\"estado\": \"São Paulo\",\n\t\t\t\t\t\"cidade\": \"São José dos Campos\",\n\t\t\t\t\t\"bairro\": \"Interlagos\",\n\t\t\t\t\t\"rua\": \"Rua. Antônio Boarini\",\n\t\t\t\t\t\"numero\": \"3000\",\n\t\t\t\t\t\"codigoPostal\": \"12229-130\",\n\t\t\t\t\t\"informacoesAdicionais\": null\n\t\t\t\t},\n\t\t\t\t\"documentos\": [\n\t\t\t\t\t{\n\t\t\t\t\t\t\"id\": 1,\n\t\t\t\t\t\t\"tipo\": \"CPF\",\n\t\t\t\t\t\t\"dataEmissao\": \"2023-06-12T18:09:57.238+00:00\",\n\t\t\t\t\t\t\"numero\": \"49985842863\"\n\t\t\t\t\t}\n\t\t\t\t],\n\t\t\t\t\"emails\": [\n\t\t\t\t\t{\n\t\t\t\t\t\t\"id\": 1,\n\t\t\t\t\t\t\"endereco\": \"edu@gmail.com\"\n\t\t\t\t\t}\n\t\t\t\t],\n\t\t\t\t\"credenciais\": [\n\t\t\t\t\t{\n\t\t\t\t\t\t\"id\": 1,\n\t\t\t\t\t\t\"criacao\": \"2023-06-12T18:09:57.238+00:00\",\n\t\t\t\t\t\t\"ultimoAcesso\": \"2023-06-12T18:09:57.238+00:00\",\n\t\t\t\t\t\t\"inativo\": false,\n\t\t\t\t\t\t\"nomeUsuario\": \"carlosfalandes\",\n\t\t\t\t\t\t\"senha\": \"fatec\"\n\t\t\t\t\t}\n\t\t\t\t],\n\t\t\t\t\"mercadorias\": [],\n\t\t\t\t\"vendas\": [],\n\t\t\t\t\"veiculos\": []\n\t\t\t},\n\t\t\t\"mercadorias\": [\n\t\t\t\t{\n\t\t\t\t\t\"id\": 1,\n\t\t\t\t\t\"validade\": \"2023-06-12T18:09:57.238+00:00\",\n\t\t\t\t\t\"fabricao\": \"2023-06-12T18:09:57.238+00:00\",\n\t\t\t\t\t\"cadastro\": \"2023-06-12T18:09:57.238+00:00\",\n\t\t\t\t\t\"nome\": \"Roda de liga leve modelo Volkswagen Golf\",\n\t\t\t\t\t\"quantidade\": 50,\n\t\t\t\t\t\"valor\": 350.0,\n\t\t\t\t\t\"descricao\": \"Roda de liga leve original de fábrica da Volkswagen para modelos do tipo hatchback\"\n\t\t\t\t}\n\t\t\t],\n\t\t\t\"servicos\": [\n\t\t\t\t{\n\t\t\t\t\t\"id\": 1,\n\t\t\t\t\t\"nome\": \"Troca de rodas esportivas\",\n\t\t\t\t\t\"valor\": 150.0,\n\t\t\t\t\t\"descricao\": \"Substituição das rodas do carro por modelos esportivos\"\n\t\t\t\t}\n\t\t\t]\n\t\t}\n\t\t]\n\t\t}"},"parameters":[],"headers":[{"name":"Content-Type","value":"application/json"}],"authentication":{},"metaSortKey":-1686592591082,"isPrivate":false,"settingStoreCookies":true,"settingSendCookies":true,"settingDisableRenderRequestBody":false,"settingEncodeUrl":true,"settingRebuildPath":true,"settingFollowRedirects":"global","_type":"request"},{"_id":"req_5f8ce616c7714ce4bdf7c9b289122a35","parentId":"fld_6e1fe355c9a04ce98030968a350be86c","modified":1686857294461,"created":1686593371811,"url":"http://localhost:8080/veiculo/cadastrar/1","name":"Cadastro","description":"","method":"POST","body":{"mimeType":"application/json","text":"{\n\t\"tipo\": \"SUV\",\n\t\"modelo\": \"Goaaaaaaaaaal\",\n\t\"placa\": \"XYZ-1234\",\n\t\"vendas\": [\n\t\t{\n\t\t\t\"id\": 1,\n\t\t\t\"cadastro\": \"2023-06-12T18:09:57.238+00:00\",\n\t\t\t\"identificacao\": \"1234698745\",\n\t\t\t\"funcionario\": {\n\t\t\t\t\"id\": 1,\n\t\t\t\t\"nome\": \"Carlos Eduardo Falandes\",\n\t\t\t\t\"nomeSocial\": \"Edu\",\n\t\t\t\t\"perfis\": [\n\t\t\t\t\t\"FUNCIONARIO\"\n\t\t\t\t],\n\t\t\t\t\"telefones\": [\n\t\t\t\t\t{\n\t\t\t\t\t\t\"id\": 2,\n\t\t\t\t\t\t\"ddd\": \"012\",\n\t\t\t\t\t\t\"numero\": \"988372758\"\n\t\t\t\t\t}\n\t\t\t\t],\n\t\t\t\t\"endereco\": {\n\t\t\t\t\t\"id\": 2,\n\t\t\t\t\t\"estado\": \"São Paulo\",\n\t\t\t\t\t\"cidade\": \"São José dos Campos\",\n\t\t\t\t\t\"bairro\": \"Interlagos\",\n\t\t\t\t\t\"rua\": \"Rua. Antônio Boarini\",\n\t\t\t\t\t\"numero\": \"3000\",\n\t\t\t\t\t\"codigoPostal\": \"12229-130\",\n\t\t\t\t\t\"informacoesAdicionais\": null\n\t\t\t\t},\n\t\t\t\t\"documentos\": [\n\t\t\t\t\t{\n\t\t\t\t\t\t\"id\": 1,\n\t\t\t\t\t\t\"tipo\": \"CPF\",\n\t\t\t\t\t\t\"dataEmissao\": \"2023-06-12T18:09:57.238+00:00\",\n\t\t\t\t\t\t\"numero\": \"49985842863\"\n\t\t\t\t\t}\n\t\t\t\t],\n\t\t\t\t\"emails\": [\n\t\t\t\t\t{\n\t\t\t\t\t\t\"id\": 1,\n\t\t\t\t\t\t\"endereco\": \"edu@gmail.com\"\n\t\t\t\t\t}\n\t\t\t\t],\n\t\t\t\t\"credenciais\": [\n\t\t\t\t\t{\n\t\t\t\t\t\t\"id\": 1,\n\t\t\t\t\t\t\"criacao\": \"2023-06-12T18:09:57.238+00:00\",\n\t\t\t\t\t\t\"ultimoAcesso\": \"2023-06-12T18:09:57.238+00:00\",\n\t\t\t\t\t\t\"inativo\": false,\n\t\t\t\t\t\t\"nomeUsuario\": \"carlosfalandes\",\n\t\t\t\t\t\t\"senha\": \"fatec\"\n\t\t\t\t\t}\n\t\t\t\t],\n\t\t\t\t\"mercadorias\": [],\n\t\t\t\t\"vendas\": [],\n\t\t\t\t\"veiculos\": []\n\t\t\t},\n\t\t\t\"mercadorias\": [\n\t\t\t\t{\n\t\t\t\t\t\"id\": 1,\n\t\t\t\t\t\"validade\": \"2023-06-12T18:09:57.238+00:00\",\n\t\t\t\t\t\"fabricao\": \"2023-06-12T18:09:57.238+00:00\",\n\t\t\t\t\t\"cadastro\": \"2023-06-12T18:09:57.238+00:00\",\n\t\t\t\t\t\"nome\": \"Roda de liga leve modelo Volkswagen Golf\",\n\t\t\t\t\t\"quantidade\": 50,\n\t\t\t\t\t\"valor\": 350.0,\n\t\t\t\t\t\"descricao\": \"Roda de liga leve original de fábrica da Volkswagen para modelos do tipo hatchback\"\n\t\t\t\t}\n\t\t\t],\n\t\t\t\"servicos\": [\n\t\t\t\t{\n\t\t\t\t\t\"id\": 1,\n\t\t\t\t\t\"nome\": \"Troca de rodas esportivas\",\n\t\t\t\t\t\"valor\": 150.0,\n\t\t\t\t\t\"descricao\": \"Substituição das rodas do carro por modelos esportivos\"\n\t\t\t\t}\n\t\t\t]\n\t\t}\n\t\t]\n\t\t}"},"parameters":[],"headers":[{"name":"Content-Type","value":"application/json"}],"authentication":{},"metaSortKey":-1686592515480,"isPrivate":false,"settingStoreCookies":true,"settingSendCookies":true,"settingDisableRenderRequestBody":false,"settingEncodeUrl":true,"settingRebuildPath":true,"settingFollowRedirects":"global","_type":"request"},{"_id":"req_386738f113904f97b7e5bb2887114e8f","parentId":"fld_6e1fe355c9a04ce98030968a350be86c","modified":1686857308279,"created":1686593371801,"url":"http://localhost:8080/veiculo/veiculo/1","name":"Veiculo especifico","description":"","method":"GET","body":{},"parameters":[],"headers":[],"authentication":{},"metaSortKey":-1686592471109,"isPrivate":false,"settingStoreCookies":true,"settingSendCookies":true,"settingDisableRenderRequestBody":false,"settingEncodeUrl":true,"settingRebuildPath":true,"settingFollowRedirects":"global","_type":"request"},{"_id":"req_b86c84fd8bf94223aef8598466574f42","parentId":"fld_6e1fe355c9a04ce98030968a350be86c","modified":1686857315550,"created":1686593371781,"url":"http://localhost:8080/veiculo/veiculos","name":"Visualizar","description":"","method":"GET","body":{},"parameters":[],"headers":[],"authentication":{},"metaSortKey":-1686592405521,"isPrivate":false,"settingStoreCookies":true,"settingSendCookies":true,"settingDisableRenderRequestBody":false,"settingEncodeUrl":true,"settingRebuildPath":true,"settingFollowRedirects":"global","_type":"request"},{"_id":"req_7eb91753ffe74698933ea076bd50c608","parentId":"fld_76d12a654dbe4cfe94f99b0914589d67","modified":1686593113588,"created":1686592889300,"url":"http://localhost:8080/servico/excluir/1","name":"Deletar","description":"","method":"DELETE","body":{"mimeType":"application/json","text":"{\n\t\"id\": 1\n}"},"parameters":[],"headers":[{"name":"Content-Type","value":"application/json"}],"authentication":{},"metaSortKey":-1686592671298,"isPrivate":false,"settingStoreCookies":true,"settingSendCookies":true,"settingDisableRenderRequestBody":false,"settingEncodeUrl":true,"settingRebuildPath":true,"settingFollowRedirects":"global","_type":"request"},{"_id":"fld_76d12a654dbe4cfe94f99b0914589d67","parentId":"wrk_0b32a91f72644d56a1e198cfc3dcaf96","modified":1686593375934,"created":1686592889254,"name":"Serviço","description":"","environment":{},"environmentPropertyOrder":null,"metaSortKey":-1686591690482.6562,"_type":"request_group"},{"_id":"req_c0a2b24e78994450b5db0695811e3471","parentId":"fld_76d12a654dbe4cfe94f99b0914589d67","modified":1686855670740,"created":1686592889288,"url":"http://localhost:8080/servico/atualizar/1","name":"Atualizar","description":"","method":"PUT","body":{"mimeType":"application/json","text":"\t{\n\t\t\"id\": 1,\n\t\t\"nome\": \"Troca de rodas esportivas\",\n\t\t\"valor\": 150000.0,\n\t\t\"descricao\": \"Substituição das rodas do carro por modelos esportivos\"\n\t}"},"parameters":[],"headers":[{"name":"Content-Type","value":"application/json"}],"authentication":{},"metaSortKey":-1686592591082,"isPrivate":false,"settingStoreCookies":true,"settingSendCookies":true,"settingDisableRenderRequestBody":false,"settingEncodeUrl":true,"settingRebuildPath":true,"settingFollowRedirects":"global","_type":"request"},{"_id":"req_7ae315fc07c14cc7ace5a243ee042ca1","parentId":"fld_76d12a654dbe4cfe94f99b0914589d67","modified":1686857326037,"created":1686592889275,"url":"http://localhost:8080/servico/cadastrar/1","name":"Cadastro","description":"","method":"POST","body":{"mimeType":"application/json","text":"\t{\n\t\t\"nome\": \"Troca de rodas\",\n\t\t\"valor\": 150.0,\n\t\t\"descricao\": \"Substituição das rodas do carro por modelos esportivos\"\n\t}"},"parameters":[],"headers":[{"name":"Content-Type","value":"application/json"}],"authentication":{},"metaSortKey":-1686592515480,"isPrivate":false,"settingStoreCookies":true,"settingSendCookies":true,"settingDisableRenderRequestBody":false,"settingEncodeUrl":true,"settingRebuildPath":true,"settingFollowRedirects":"global","_type":"request"},{"_id":"req_9bac9b8c57874080ac37da3870c11cd3","parentId":"fld_76d12a654dbe4cfe94f99b0914589d67","modified":1686857334509,"created":1686592889266,"url":"http://localhost:8080/servico/servico/1","name":"Serviço especifico","description":"","method":"GET","body":{},"parameters":[],"headers":[],"authentication":{},"metaSortKey":-1686592471109,"isPrivate":false,"settingStoreCookies":true,"settingSendCookies":true,"settingDisableRenderRequestBody":false,"settingEncodeUrl":true,"settingRebuildPath":true,"settingFollowRedirects":"global","_type":"request"},{"_id":"req_ea4b1dca239e427ea51e50fcb6e309ed","parentId":"fld_76d12a654dbe4cfe94f99b0914589d67","modified":1686857340345,"created":1686592889258,"url":"http://localhost:8080/servico/servicos","name":"Visualizar","description":"","method":"GET","body":{},"parameters":[],"headers":[],"authentication":{},"metaSortKey":-1686592405521,"isPrivate":false,"settingStoreCookies":true,"settingSendCookies":true,"settingDisableRenderRequestBody":false,"settingEncodeUrl":true,"settingRebuildPath":true,"settingFollowRedirects":"global","_type":"request"},{"_id":"req_fcf9a92514c34105bce6b66b25fb7473","parentId":"fld_a030f8f70d3f4bcf80cfd1777a670a1f","modified":1686592756852,"created":1686592671298,"url":"http://localhost:8080/mercadoria/excluir/1","name":"Deletar","description":"","method":"DELETE","body":{},"parameters":[],"headers":[],"authentication":{},"metaSortKey":-1686592671298,"isPrivate":false,"settingStoreCookies":true,"settingSendCookies":true,"settingDisableRenderRequestBody":false,"settingEncodeUrl":true,"settingRebuildPath":true,"settingFollowRedirects":"global","_type":"request"},{"_id":"fld_a030f8f70d3f4bcf80cfd1777a670a1f","parentId":"wrk_0b32a91f72644d56a1e198cfc3dcaf96","modified":1686592895832,"created":1686592403915,"name":"Mercadoria","description":"","environment":{},"environmentPropertyOrder":null,"metaSortKey":-1686591588563.75,"_type":"request_group"},{"_id":"req_0a8b8ac4151c48828afef375139a4fb0","parentId":"fld_a030f8f70d3f4bcf80cfd1777a670a1f","modified":1686855623245,"created":1686592591082,"url":"http://localhost:8080/mercadoria/atualizar/1","name":"Atualizar","description":"","method":"PUT","body":{"mimeType":"application/json","text":"{\n\t\"id\": 1,\n\t\"validade\": \"2023-06-12T17:53:08.301+00:00\",\n\t\"fabricao\": \"2023-06-12T17:53:08.301+00:00\",\n\t\"cadastro\": \"2023-06-12T17:53:08.301+00:00\",\n\t\"nome\": \"Roda de liga leve modelo Volkswagen Golf\",\n\t\"quantidade\": 5000,\n\t\"valor\": 350.0,\n\t\"descricao\": \"Roda de liga leve original de fábrica da Volkswagen para modelos do tipo hatchback\"\n}"},"parameters":[],"headers":[{"name":"Content-Type","value":"application/json"}],"authentication":{},"metaSortKey":-1686592591082,"isPrivate":false,"settingStoreCookies":true,"settingSendCookies":true,"settingDisableRenderRequestBody":false,"settingEncodeUrl":true,"settingRebuildPath":true,"settingFollowRedirects":"global","_type":"request"},{"_id":"req_5191875f0562476b813142c6f8678189","parentId":"fld_a030f8f70d3f4bcf80cfd1777a670a1f","modified":1686857346907,"created":1686592515480,"url":"http://localhost:8080/mercadoria/cadastrar/1","name":"Cadastro","description":"","method":"POST","body":{"mimeType":"application/json","text":"{\n\t\"validade\": \"2023-06-12T17:53:08.301+00:00\",\n\t\"fabricao\": \"2023-06-12T17:53:08.301+00:00\",\n\t\"cadastro\": \"2023-06-12T17:53:08.301+00:00\",\n\t\"nome\": \"Roda de liga leve modelo Volkswagen Golf\",\n\t\"quantidade\": 50,\n\t\"valor\": 350.0,\n\t\"descricao\": \"Roda de liga leve original de fábrica da Volkswagen para modelos do tipo hatchback\"\n}"},"parameters":[],"headers":[{"name":"Content-Type","value":"application/json"}],"authentication":{},"metaSortKey":-1686592515480,"isPrivate":false,"settingStoreCookies":true,"settingSendCookies":true,"settingDisableRenderRequestBody":false,"settingEncodeUrl":true,"settingRebuildPath":true,"settingFollowRedirects":"global","_type":"request"},{"_id":"req_240b89bcad3c45879694ff67f2a31eb4","parentId":"fld_a030f8f70d3f4bcf80cfd1777a670a1f","modified":1686857353679,"created":1686592471109,"url":"http://localhost:8080/mercadoria/mercadoria/1","name":"Mercadoria visualizar","description":"","method":"GET","body":{},"parameters":[],"headers":[],"authentication":{},"metaSortKey":-1686592471109,"isPrivate":false,"settingStoreCookies":true,"settingSendCookies":true,"settingDisableRenderRequestBody":false,"settingEncodeUrl":true,"settingRebuildPath":true,"settingFollowRedirects":"global","_type":"request"},{"_id":"req_1bcd27ee3410407cbadfeea955b16942","parentId":"fld_a030f8f70d3f4bcf80cfd1777a670a1f","modified":1686857359901,"created":1686592405521,"url":"http://localhost:8080/mercadoria/mercadorias","name":"Visualizar","description":"","method":"GET","body":{},"parameters":[],"headers":[],"authentication":{},"metaSortKey":-1686592405521,"isPrivate":false,"settingStoreCookies":true,"settingSendCookies":true,"settingDisableRenderRequestBody":false,"settingEncodeUrl":true,"settingRebuildPath":true,"settingFollowRedirects":"global","_type":"request"},{"_id":"req_49c8d9ee93af4ec8920ca5ee9f21e7c7","parentId":"fld_f075f34ff6cd4091b2b4139c14b9e951","modified":1686591768083,"created":1686591673063,"url":"http://localhost:8080/empresa/atualizar","name":"Atualizar","description":"","method":"PUT","body":{"mimeType":"application/json","text":"{\n\t\"id\": 1,\n\t\"razaoSocial\": \"LTDA Help carros\",\n\t\"nomeFantasia\": \"Help carros\",\n\t\"telefones\": [\n\t\t{\n\t\t\t\"ddd\": \"011\",\n\t\t\t\"numero\": \"986454527\"\n\t\t}\n\t],\n\t\"endereco\": {\n\t\t\"estado\": \"São Paulo\",\n\t\t\"cidade\": \"São Jasé dos Campos\",\n\t\t\"bairro\": \"Centro\",\n\t\t\"rua\": \"Av. Cidade Jardim\",\n\t\t\"numero\": \"2000\",\n\t\t\"codigoPostal\": \"12233-002\",\n\t\t\"informacoesAdicionais\": null\n\t}\n}"},"parameters":[],"headers":[{"name":"Content-Type","value":"application/json"}],"authentication":{},"metaSortKey":-1686591673063,"isPrivate":false,"settingStoreCookies":true,"settingSendCookies":true,"settingDisableRenderRequestBody":false,"settingEncodeUrl":true,"settingRebuildPath":true,"settingFollowRedirects":"global","_type":"request"},{"_id":"fld_f075f34ff6cd4091b2b4139c14b9e951","parentId":"wrk_0b32a91f72644d56a1e198cfc3dcaf96","modified":1686591316780,"created":1686591316780,"name":"Empresa","description":"","environment":{},"environmentPropertyOrder":null,"metaSortKey":-1686591316780,"_type":"request_group"},{"_id":"req_a6c7670c0fb54d0a8debb18381766fed","parentId":"fld_f075f34ff6cd4091b2b4139c14b9e951","modified":1686857365542,"created":1686591474022,"url":"http://localhost:8080/empresa/cadastrar","name":"Cadastro","description":"","method":"POST","body":{"mimeType":"application/json","text":"{\n\t\"razaoSocial\": \"LTDA Help carros\",\n\t\"nomeFantasia\": \"Help carros\",\n\t\"telefones\": [\n\t\t{\n\t\t\t\"ddd\": \"011\",\n\t\t\t\"numero\": \"986454527\"\n\t\t}\n\t],\n\t\"endereco\": {\n\t\t\"estado\": \"São Paulo\",\n\t\t\"cidade\": \"São Jasé dos Campos\",\n\t\t\"bairro\": \"Centro\",\n\t\t\"rua\": \"Av. Cidade Jardim\",\n\t\t\"numero\": \"2000\",\n\t\t\"codigoPostal\": \"12233-002\",\n\t\t\"informacoesAdicionais\": null\n\t}\n}"},"parameters":[],"headers":[{"name":"Content-Type","value":"application/json"}],"authentication":{},"metaSortKey":-1686591474022,"isPrivate":false,"settingStoreCookies":true,"settingSendCookies":true,"settingDisableRenderRequestBody":false,"settingEncodeUrl":true,"settingRebuildPath":true,"settingFollowRedirects":"global","_type":"request"},{"_id":"req_aee307454c2645c1815c949dade40e53","parentId":"fld_f075f34ff6cd4091b2b4139c14b9e951","modified":1686857370277,"created":1686591411084,"url":"http://localhost:8080/empresa/empresas1","name":"Empresa especifica","description":"","method":"GET","body":{},"parameters":[],"headers":[],"authentication":{},"metaSortKey":-1686591411084,"isPrivate":false,"settingStoreCookies":true,"settingSendCookies":true,"settingDisableRenderRequestBody":false,"settingEncodeUrl":true,"settingRebuildPath":true,"settingFollowRedirects":"global","_type":"request"},{"_id":"req_b45e4fbcb4534dac810fe30fb215c8c1","parentId":"fld_f075f34ff6cd4091b2b4139c14b9e951","modified":1686857376071,"created":1686591318222,"url":"http://localhost:8080/empresa/empresas","name":"Visualizar","description":"","method":"GET","body":{},"parameters":[],"headers":[],"authentication":{},"metaSortKey":-1686591318222,"isPrivate":false,"settingStoreCookies":true,"settingSendCookies":true,"settingDisableRenderRequestBody":false,"settingEncodeUrl":true,"settingRebuildPath":true,"settingFollowRedirects":"global","_type":"request"},{"_id":"req_b4568a2141094e6e9f8b5b5c99831d60","parentId":"fld_f075f34ff6cd4091b2b4139c14b9e951","modified":1686591830308,"created":1686591795446,"url":"http://localhost:8080/empresa/excluir/1","name":"Deletar","description":"","method":"DELETE","body":{},"parameters":[],"headers":[],"authentication":{},"metaSortKey":-1686591318172,"isPrivate":false,"settingStoreCookies":true,"settingSendCookies":true,"settingDisableRenderRequestBody":false,"settingEncodeUrl":true,"settingRebuildPath":true,"settingFollowRedirects":"global","_type":"request"},{"_id":"req_878641ac15774de58fee5d7ad17027b3","parentId":"fld_d10884fc168d40d4a25324e3cf4f46b1","modified":1686857381954,"created":1683944929425,"url":"http://localhost:9080/telefone/cadastrar","name":"Adição telefone","description":"","method":"POST","body":{"mimeType":"application/json","text":"{\n\t\"id\": 1,\n\t\"telefones\": \n\t[{\n\t\t\t\"ddd\": \"12\",\n\t\t\t\"numero\": \"981234576\"\n\t}]\n}"},"parameters":[],"headers":[{"name":"Content-Type","value":"application/json"}],"authentication":{},"metaSortKey":-1683071881801.5,"isPrivate":false,"settingStoreCookies":true,"settingSendCookies":true,"settingDisableRenderRequestBody":false,"settingEncodeUrl":true,"settingRebuildPath":true,"settingFollowRedirects":"global","_type":"request"},{"_id":"fld_d10884fc168d40d4a25324e3cf4f46b1","parentId":"wrk_0b32a91f72644d56a1e198cfc3dcaf96","modified":1683071880756,"created":1683071880756,"name":"Telefones","description":"","environment":{},"environmentPropertyOrder":null,"metaSortKey":-1683071880756,"_type":"request_group"},{"_id":"req_1d58b44385294483804876032255510b","parentId":"fld_d10884fc168d40d4a25324e3cf4f46b1","modified":1686857387533,"created":1683071881814,"url":"http://localhost:9080/telefone/telefones","name":"Visualizar","description":"","method":"GET","body":{},"parameters":[],"headers":[],"authentication":{},"metaSortKey":-1683071881795.25,"isPrivate":false,"settingStoreCookies":true,"settingSendCookies":true,"settingDisableRenderRequestBody":false,"settingEncodeUrl":true,"settingRebuildPath":true,"settingFollowRedirects":"global","_type":"request"},{"_id":"req_bd5bf083223243e49455b7f8491de40a","parentId":"fld_d10884fc168d40d4a25324e3cf4f46b1","modified":1686857395209,"created":1683844712808,"url":"http://localhost:9080/telefone/telefone/1","name":"Telefone especifico","description":"","method":"GET","body":{},"parameters":[],"headers":[],"authentication":{},"metaSortKey":-1683071881789,"isPrivate":false,"settingStoreCookies":true,"settingSendCookies":true,"settingDisableRenderRequestBody":false,"settingEncodeUrl":true,"settingRebuildPath":true,"settingFollowRedirects":"global","_type":"request"},{"_id":"req_6af83775949247baa0dbed13bb3e1fa2","parentId":"fld_d10884fc168d40d4a25324e3cf4f46b1","modified":1686855283173,"created":1679487344170,"url":"http://localhost:9080/telefone/excluir","name":"Remove telefone","description":"","method":"DELETE","body":{},"parameters":[],"headers":[],"authentication":{},"metaSortKey":-1683071881764,"isPrivate":false,"settingStoreCookies":true,"settingSendCookies":true,"settingDisableRenderRequestBody":false,"settingEncodeUrl":true,"settingRebuildPath":true,"settingFollowRedirects":"global","_type":"request"},{"_id":"req_e1150c3cd17c453f8bdeb2ce42440ac0","parentId":"fld_d10884fc168d40d4a25324e3cf4f46b1","modified":1686596117250,"created":1683073280027,"url":"http://localhost:9080/telefone/atualizar","name":"Atualizar ","description":"","method":"PUT","body":{"mimeType":"application/json","text":"{\n\t\t\t\"id\": 1,\n\t\t\t\"ddd\": \"21\",\n\t\t\t\"numero\": \"9819009\"\n}"},"parameters":[],"headers":[{"name":"Content-Type","value":"application/json"}],"authentication":{},"metaSortKey":-1683071881714,"isPrivate":false,"settingStoreCookies":true,"settingSendCookies":true,"settingDisableRenderRequestBody":false,"settingEncodeUrl":true,"settingRebuildPath":true,"settingFollowRedirects":"global","_type":"request"},{"_id":"req_68fd15566621497f87000a7645e2da14","parentId":"fld_6f03e75adf4a4e7287aad2fffaf222cb","modified":1686857402614,"created":1679483560535,"url":"http://localhost:8080/documento/cadastrar","name":"Adição documento","description":"","method":"POST","body":{"mimeType":"application/json","text":"{\n\t\"id\": 1,\n\t\"documentos\": \n\t\t\t[{\n\t\t\t\t\"tipo\": \"CPF\",\n\t\t\t\t\"numero\": \"234455\"\n\t\t\t}]\n}"},"parameters":[],"headers":[{"name":"Content-Type","value":"application/json"}],"authentication":{},"metaSortKey":-1683071436945.75,"isPrivate":false,"settingStoreCookies":true,"settingSendCookies":true,"settingDisableRenderRequestBody":false,"settingEncodeUrl":true,"settingRebuildPath":true,"settingFollowRedirects":"global","_type":"request"},{"_id":"fld_6f03e75adf4a4e7287aad2fffaf222cb","parentId":"wrk_0b32a91f72644d56a1e198cfc3dcaf96","modified":1683071265187,"created":1683071265187,"name":"Documentos","description":"","environment":{},"environmentPropertyOrder":null,"metaSortKey":-1683071265187,"_type":"request_group"},{"_id":"req_ba892c0256544f148587e0b9d045e9af","parentId":"fld_6f03e75adf4a4e7287aad2fffaf222cb","modified":1686857408864,"created":1683071436952,"url":"http://localhost:8080/documento/documentos","name":"Visualizar","description":"","method":"GET","body":{},"parameters":[],"headers":[],"authentication":{},"metaSortKey":-1683071436936.375,"isPrivate":false,"settingStoreCookies":true,"settingSendCookies":true,"settingDisableRenderRequestBody":false,"settingEncodeUrl":true,"settingRebuildPath":true,"settingFollowRedirects":"global","_type":"request"},{"_id":"req_510857a33e6e4ea3bcbf96f010c09d94","parentId":"fld_6f03e75adf4a4e7287aad2fffaf222cb","modified":1686857418456,"created":1683843989473,"url":"http://localhost:8080/documento/documento/1","name":"Documento especifico","description":"","method":"GET","body":{},"parameters":[],"headers":[],"authentication":{},"metaSortKey":-1683071436927,"isPrivate":false,"settingStoreCookies":true,"settingSendCookies":true,"settingDisableRenderRequestBody":false,"settingEncodeUrl":true,"settingRebuildPath":true,"settingFollowRedirects":"global","_type":"request"},{"_id":"req_41717ead46d74046b7d464f15b5c587b","parentId":"fld_6f03e75adf4a4e7287aad2fffaf222cb","modified":1686855509211,"created":1679487905667,"url":"http://localhost:8080/documento/excluir","name":"Delete documento","description":"","method":"DELETE","body":{},"parameters":[],"headers":[],"authentication":{},"metaSortKey":-1683071436902,"isPrivate":false,"settingStoreCookies":true,"settingSendCookies":true,"settingDisableRenderRequestBody":false,"settingEncodeUrl":true,"settingRebuildPath":true,"settingFollowRedirects":"global","_type":"request"},{"_id":"req_9352d02e5d3b4816ab925f8a9f3f370b","parentId":"fld_6f03e75adf4a4e7287aad2fffaf222cb","modified":1686855512455,"created":1683073271815,"url":"http://localhost:8080/documento/atualizar","name":"Atualizar ","description":"","method":"PUT","body":{"mimeType":"application/json","text":"{\n\t\t\t\"id\": 1,\n\t\t\t\"tipo\": \"RG\",\n\t\t\t\"numero\": \"151123123131\"\n}"},"parameters":[],"headers":[{"name":"Content-Type","value":"application/json"}],"authentication":{},"metaSortKey":-1683071436852,"isPrivate":false,"settingStoreCookies":true,"settingSendCookies":true,"settingDisableRenderRequestBody":false,"settingEncodeUrl":true,"settingRebuildPath":true,"settingFollowRedirects":"global","_type":"request"},{"_id":"req_099a1cef7c074ffba82902c1bb58af7c","parentId":"fld_cdbff34baa544a2fb33e14fd8f3ad40c","modified":1686857425077,"created":1683944520936,"url":"http://localhost:8080/endereco/cadastrar","name":"Adição endereço","description":"","method":"POST","body":{"mimeType":"application/json","text":"{\n\t\t\t\"estado\": \"São Paulo\",\n\t\t\t\"cidade\": \"São José dos Campos\",\n\t\t\t\"bairro\": \"Satélite\",\n\t\t\t\"rua\": \"Leblon\",\n\t\t\t\"numero\": \"100\",\n\t\t\t\"codigoPostal\": \"22021001\",\n\t\t\t\"informacoesAdicionais\": \"Escola\"\n}"},"parameters":[],"headers":[{"name":"Content-Type","value":"application/json"}],"authentication":{},"metaSortKey":-1683944520936,"isPrivate":false,"settingStoreCookies":true,"settingSendCookies":true,"settingDisableRenderRequestBody":false,"settingEncodeUrl":true,"settingRebuildPath":true,"settingFollowRedirects":"global","_type":"request"},{"_id":"fld_cdbff34baa544a2fb33e14fd8f3ad40c","parentId":"wrk_0b32a91f72644d56a1e198cfc3dcaf96","modified":1683069759033,"created":1683069759033,"name":"Endereços","description":"","environment":{},"environmentPropertyOrder":null,"metaSortKey":-1683069759033,"_type":"request_group"},{"_id":"req_f8fd77076cc142bf87df4107af9f25d4","parentId":"fld_cdbff34baa544a2fb33e14fd8f3ad40c","modified":1686857431703,"created":1683069760655,"url":"http://localhost:8080/endereco/enderecos","name":"Visualizar","description":"","method":"GET","body":{},"parameters":[],"headers":[],"authentication":{},"metaSortKey":-1683069760655,"isPrivate":false,"settingStoreCookies":true,"settingSendCookies":true,"settingDisableRenderRequestBody":false,"settingEncodeUrl":true,"settingRebuildPath":true,"settingFollowRedirects":"global","_type":"request"},{"_id":"req_46efa4672c184a1f8ba82c39eb5a9e02","parentId":"fld_cdbff34baa544a2fb33e14fd8f3ad40c","modified":1686857443086,"created":1683842575189,"url":"http://localhost:8080/endereco/endereco/1","name":"Endereço especifico ","description":"","method":"GET","body":{},"parameters":[],"headers":[],"authentication":{},"metaSortKey":-1683069760617.5,"isPrivate":false,"settingStoreCookies":true,"settingSendCookies":true,"settingDisableRenderRequestBody":false,"settingEncodeUrl":true,"settingRebuildPath":true,"settingFollowRedirects":"global","_type":"request"},{"_id":"req_4cb31b1abba64c529df17fb792563ba4","parentId":"fld_cdbff34baa544a2fb33e14fd8f3ad40c","modified":1686855547998,"created":1683153671545,"url":"http://localhost:8080/endereco/excluir","name":"Delete endereço","description":"","method":"DELETE","body":{"mimeType":"application/json","text":"{\n\t\"id\": 1\n}"},"parameters":[],"headers":[{"name":"Content-Type","value":"application/json"}],"authentication":{},"metaSortKey":-1683069760580,"isPrivate":false,"settingStoreCookies":true,"settingSendCookies":true,"settingDisableRenderRequestBody":false,"settingEncodeUrl":true,"settingRebuildPath":true,"settingFollowRedirects":"global","_type":"request"},{"_id":"req_80d477d9b5154a36a0476929ad8304cc","parentId":"fld_cdbff34baa544a2fb33e14fd8f3ad40c","modified":1686855551365,"created":1683073263162,"url":"http://localhost:8080/endereco/atualizar","name":"Atualizar ","description":"","method":"PUT","body":{"mimeType":"application/json","text":"{\n\t\t\"id\": 1,\n\t\t\"estado\": \"Ri0000o\",\n\t\t\"cidade\": \"Rio de Janeiro\",\n\t\t\"bairro\": \"Copacabana\",\n\t\t\"rua\": \"Avenida Atlântica\",\n\t\t\"numero\": \"1702\",\n\t\t\"codigoPostal\": \"22021001\",\n\t\t\"informacoesAdicionais\": \"Hotel Copacabana palace\"\n}"},"parameters":[],"headers":[{"name":"Content-Type","value":"application/json"}],"authentication":{},"metaSortKey":-1683069760555,"isPrivate":false,"settingStoreCookies":true,"settingSendCookies":true,"settingDisableRenderRequestBody":false,"settingEncodeUrl":true,"settingRebuildPath":true,"settingFollowRedirects":"global","_type":"request"},{"_id":"req_e842ea072b7647d4bde61a7d5b31bf6e","parentId":"fld_cf67ef5cb3ed4cc5aa4d917d77e69bbd","modified":1686856912745,"created":1679485427102,"url":"http://localhost:8080/usuario/cadastro/1","name":"Cadastro","description":"","method":"POST","body":{"mimeType":"application/json","text":"{\n\t\"nome\": \"Bernadete\",\n\t\"nomeSocial\": \"Ju\",\n\t\"perfis\": [\n\t\t\"FORNECEDOR\"\n\t],\n\t\"telefones\": [],\n\t\"endereco\": {\n\t\t\"estado\": \"São Paulo\",\n\t\t\"cidade\": \"São Paulo\",\n\t\t\"bairro\": \"Vila Mariana\",\n\t\t\"rua\": \"Rua da Consolação\",\n\t\t\"numero\": \"123\",\n\t\t\"codigoPostal\": \"01001-000\",\n\t\t\"informacoesAdicionais\": null\n\t},\n\t\"documentos\": [\n\t\t{\n\t\t\t\"tipo\": \"CNPJ\",\n\t\t\t\"dataEmissao\": \"2023-06-12T17:15:17.011+00:00\",\n\t\t\t\"numero\": \"12345678000190\"\n\t\t}\n\t],\n\t\"emails\": [\n\t\t{\n\t\t\t\"endereco\": \"ju@gmail.com\"\n\t\t}\n\t],\n\t\"credenciais\": [\n\t\t{\n\t\t\t\"criacao\": \"2023-06-12T17:15:17.011+00:00\",\n\t\t\t\"ultimoAcesso\": \"2023-06-12T17:15:17.011+00:00\",\n\t\t\t\"inativo\": false,\n\t\t\t\"nomeUsuario\": \"juliafornecedora\",\n\t\t\t\"senha\": \"fatec\"\n\t\t}\n\t],\n\t\"mercadorias\": [\n\t\t{\n\t\t\t\"validade\": \"2023-06-12T17:15:17.011+00:00\",\n\t\t\t\"fabricao\": \"2023-06-12T17:15:17.011+00:00\",\n\t\t\t\"cadastro\": \"2023-06-12T17:15:17.011+00:00\",\n\t\t\t\"nome\": \"Roda de liga leve modelo Volkswagen Golf\",\n\t\t\t\"quantidade\": 50,\n\t\t\t\"valor\": 350.0,\n\t\t\t\"descricao\": \"Roda de liga leve original de fábrica da Volkswagen para modelos do tipo hatchback\"\n\t\t}\n\t\t]\n}"},"parameters":[],"headers":[{"name":"Content-Type","value":"application/json"}],"authentication":{},"metaSortKey":-1683170287009.5,"isPrivate":false,"settingStoreCookies":true,"settingSendCookies":true,"settingDisableRenderRequestBody":false,"settingEncodeUrl":true,"settingRebuildPath":true,"settingFollowRedirects":"global","_type":"request"},{"_id":"fld_cf67ef5cb3ed4cc5aa4d917d77e69bbd","parentId":"wrk_0b32a91f72644d56a1e198cfc3dcaf96","modified":1686589753661,"created":1679485241501,"name":"Usuario","description":"","environment":{},"environmentPropertyOrder":null,"metaSortKey":-1679485241501,"_type":"request_group"},{"_id":"req_8a5a55f30c5c4f7a8018cb27a26fbf0b","parentId":"fld_cf67ef5cb3ed4cc5aa4d917d77e69bbd","modified":1686857490903,"created":1686855146917,"url":"http://localhost:8080/usurio/cadastrar/credencial/1","name":"cadastro credencial","description":"","method":"POST","body":{},"parameters":[],"headers":[],"authentication":{},"metaSortKey":-1681327825285.75,"isPrivate":false,"settingStoreCookies":true,"settingSendCookies":true,"settingDisableRenderRequestBody":false,"settingEncodeUrl":true,"settingRebuildPath":true,"settingFollowRedirects":"global","_type":"request"},{"_id":"req_ca51f758e13343778d5ceeef516fd629","parentId":"fld_cf67ef5cb3ed4cc5aa4d917d77e69bbd","modified":1686857497519,"created":1679485363562,"url":"http://localhost:8080/usuario/usuario/1","name":"Cliente especifico ","description":"","method":"GET","body":{},"parameters":[],"headers":[],"authentication":{},"metaSortKey":-1679485363562,"isPrivate":false,"settingStoreCookies":true,"settingSendCookies":true,"settingDisableRenderRequestBody":false,"settingEncodeUrl":true,"settingRebuildPath":true,"settingFollowRedirects":"global","_type":"request"},{"_id":"req_3daa8e53fefd4e0c897c88b450b86bef","parentId":"fld_cf67ef5cb3ed4cc5aa4d917d77e69bbd","modified":1686590143225,"created":1679487275632,"url":"http://localhost:8080/usuario/excluir/1","name":"Delete usuario","description":"","method":"DELETE","body":{"mimeType":"application/json","text":"{\n\t\"id\": 1\n}"},"parameters":[],"headers":[{"name":"Content-Type","value":"application/json"}],"authentication":{},"metaSortKey":-1679485303306.5,"isPrivate":false,"settingStoreCookies":true,"settingSendCookies":true,"settingDisableRenderRequestBody":false,"settingEncodeUrl":true,"settingRebuildPath":true,"settingFollowRedirects":"global","_type":"request"},{"_id":"req_b61902a666854cbda04d6b0c047ac8e0","parentId":"fld_cf67ef5cb3ed4cc5aa4d917d77e69bbd","modified":1686857511052,"created":1679485243051,"url":"http://localhost:8080/usuario/usuarios","name":"Visualizar","description":"","method":"GET","body":{},"parameters":[],"headers":[],"authentication":{},"metaSortKey":-1679485243051,"isPrivate":false,"settingStoreCookies":true,"settingSendCookies":true,"settingDisableRenderRequestBody":false,"settingEncodeUrl":true,"settingRebuildPath":true,"settingFollowRedirects":"global","_type":"request"},{"_id":"req_b64aa35eaebf4a78893e4cb9356e5b9d","parentId":"fld_9797a453be8b4d9e9a36bd53999531be","modified":1686857830844,"created":1679485427102,"url":"http://localhost:8080/cliente/cadastrar","name":"Cadastro","description":"","method":"POST","body":{"mimeType":"application/json","text":"{\n\t\"nome\": \"Carlos Eduardo Falandes\",\n\t\"nomeSocial\": \"Edu\",\n\t\"dataNascimento\": \"2004-06-15T11:40:11.298+00:00\",\n\t\"dataCadastro\": \"2023-03-22T11:40:11.298+00:00\",\n\t\"documentos\": [\n\t\t{\n\t\t\t\"tipo\": \"RG\",\n\t\t\t\"numero\": \"132334344\"\n\t\t},\n\t\t{\n\t\t\t\"tipo\": \"CPF\",\n\t\t\t\"numero\": \"000000000014\"\n\t\t}\n\t],\n\t\"endereco\": {\n\t\t\"estado\": \"São Paulo\",\n\t\t\"cidade\": \"São José dos Campos\",\n\t\t\"bairro\": \"Parque interlagos\",\n\t\t\"rua\": \"Antônio Boarini\",\n\t\t\"numero\": \"327\",\n\t\t\"codigoPostal\": \"22021001\",\n\t\t\"informacoesAdicionais\": \"Casa\"\n\t},\n\t\"telefones\": [\n\t\t{\n\t\t\t\"ddd\": \"12\",\n\t\t\t\"numero\": \"981234576\"\n\t\t}\n\t]\n}"},"parameters":[],"headers":[{"name":"Content-Type","value":"application/json"}],"authentication":{},"metaSortKey":-1679485427102,"isPrivate":false,"settingStoreCookies":true,"settingSendCookies":true,"settingDisableRenderRequestBody":false,"settingEncodeUrl":true,"settingRebuildPath":true,"settingFollowRedirects":"global","_type":"request"},{"_id":"fld_9797a453be8b4d9e9a36bd53999531be","parentId":"wrk_0b32a91f72644d56a1e198cfc3dcaf96","modified":1679485241501,"created":1679485241501,"name":"Clientes","description":"","environment":{},"environmentPropertyOrder":null,"metaSortKey":-1679485241501,"_type":"request_group"},{"_id":"req_a106804934b0497b8a17e55cf77a9e0b","parentId":"fld_9797a453be8b4d9e9a36bd53999531be","modified":1686857469320,"created":1679485363562,"url":"http://localhost:8080/cliente/cliente/1","name":"Cliente especifico ","description":"","method":"GET","body":{},"parameters":[],"headers":[],"authentication":{},"metaSortKey":-1679485363562,"isPrivate":false,"settingStoreCookies":true,"settingSendCookies":true,"settingDisableRenderRequestBody":false,"settingEncodeUrl":true,"settingRebuildPath":true,"settingFollowRedirects":"global","_type":"request"},{"_id":"req_f784db74b1ea407886e8e1c2b4aac34d","parentId":"fld_9797a453be8b4d9e9a36bd53999531be","modified":1686855356238,"created":1679487275632,"url":"http://localhost:8080/cliente/excluir","name":"Delete cliente","description":"","method":"DELETE","body":{},"parameters":[],"headers":[],"authentication":{},"metaSortKey":-1679485303306.5,"isPrivate":false,"settingStoreCookies":true,"settingSendCookies":true,"settingDisableRenderRequestBody":false,"settingEncodeUrl":true,"settingRebuildPath":true,"settingFollowRedirects":"global","_type":"request"},{"_id":"req_bb8414e75f574ce889c35cf3bbdff117","parentId":"fld_9797a453be8b4d9e9a36bd53999531be","modified":1686857841092,"created":1679485243051,"url":"http://localhost:8080/cliente/clientes","name":"Visualizar","description":"","method":"GET","body":{},"parameters":[],"headers":[],"authentication":{},"metaSortKey":-1679485243051,"isPrivate":false,"settingStoreCookies":true,"settingSendCookies":true,"settingDisableRenderRequestBody":false,"settingEncodeUrl":true,"settingRebuildPath":true,"settingFollowRedirects":"global","_type":"request"},{"_id":"req_0803b4b40de447ad8903b1311a1b280a","parentId":"fld_9797a453be8b4d9e9a36bd53999531be","modified":1686857848300,"created":1679486965212,"url":"http://localhost:8080/cliente/atualizar","name":"Atualizar ","description":"","method":"PUT","body":{"mimeType":"application/json","text":"{\n\t\"nome\": \"Pedrinho\",\n\t\"nomeSocial\": \"Pedro\",\n\t\"dataNascimento\": \"2002-06-15T11:40:11.298+00:00\",\n\t\"dataCadastro\": \"2023-03-22T11:40:11.298+00:00\",\n\t\"documentos\": [\n\t\t{\n\t\t\t\"id\": 1,\n\t\t\t\"tipo\": \"RG\",\n\t\t\t\"numero\": \"150000000\"\n\t\t},\n\t\t{\n\t\t\t\"id\": 2,\n\t\t\t\"tipo\": \"RG\",\n\t\t\t\"numero\": \"00000000001\"\n\t\t}\n\t],\n\t\"endereco\": {\n\t\t\"id\": 1,\n\t\t\"estado\": \"Rio de Janeiro\",\n\t\t\"cidade\": \"Rio de Janeiro\",\n\t\t\"bairro\": \"Copacabana\",\n\t\t\"rua\": \"Avenida Atlântica\",\n\t\t\"numero\": \"1702\",\n\t\t\"codigoPostal\": \"22021001\",\n\t\t\"informacoesAdicionais\": \"Hotel Copacabana palace\"\n\t},\n\t\"telefones\": [\n\t\t{\n\t\t\t\"id\": 1,\n\t\t\t\"ddd\": \"21\",\n\t\t\t\"numero\": \"981234576\"\n\t\t}\n\t]\n}"},"parameters":[],"headers":[{"name":"Content-Type","value":"application/json"}],"authentication":{},"metaSortKey":-1679485243001,"isPrivate":false,"settingStoreCookies":true,"settingSendCookies":true,"settingDisableRenderRequestBody":false,"settingEncodeUrl":true,"settingRebuildPath":true,"settingFollowRedirects":"global","_type":"request"},{"_id":"env_95f9ad45eb7c4cc6b409cf628da9eb0d","parentId":"wrk_0b32a91f72644d56a1e198cfc3dcaf96","modified":1679483553014,"created":1679483553014,"name":"Base Environment","data":{},"dataPropertyOrder":null,"color":null,"isPrivate":false,"metaSortKey":1679483553014,"_type":"environment"},{"_id":"jar_e687eef232b14a789f71c1cae5e587c9","parentId":"wrk_0b32a91f72644d56a1e198cfc3dcaf96","modified":1679483553017,"created":1679483553017,"name":"Default Jar","cookies":[],"_type":"cookie_jar"},{"_id":"spc_d6e710d91ea547fcb433cd7a8c763a72","parentId":"wrk_0b32a91f72644d56a1e198cfc3dcaf96","modified":1686857813599,"created":1686857813599,"fileName":"Untitled","contents":"","contentType":"yaml","_type":"api_spec"}]}